__init__.py
dbcache/__init__.py
dbcache/dbcache.py
dbcache/demo.py
dbcache/models/__init__.py
dbcache/models/base.py
dbcache/models/cache.py
ss_dbcache-0.0.34.dist-info/licenses/LICENSE
ss_dbcache-0.0.34.dist-info/METADATA
ss_dbcache-0.0.34.dist-info/WHEEL
ss_dbcache-0.0.34.dist-info/top_level.txt
ss_dbcache-0.0.34.dist-info/RECORD
