Metadata-Version: 2.4
Name: ss-dbcache
Version: 0.0.34
Summary: Cache Manger: cache compressed, serialised database tables as longblob in database cache table 
Author-email: Julian Briggs <julian.briggs@sheffield.ac.uk>
License-Expression: MIT
Project-URL: Homepage, https://github.com/pypa/ss-dbcache
Project-URL: Issues, https://github.com/pypa/ss-dbcache/issues
Classifier: Programming Language :: Python :: 3
Classifier: Operating System :: OS Independent
Requires-Python: >=3.12
License-File: LICENSE
Requires-Dist: configargparse
Requires-Dist: mysql-connector-python
Requires-Dist: mysqlclient
Requires-Dist: pandas
Requires-Dist: pymysql
Requires-Dist: python-dotenv
Requires-Dist: pyyaml
Requires-Dist: ss-sqlahandler
Provides-Extra: dev
Requires-Dist: black; extra == "dev"
Requires-Dist: build; extra == "dev"
Requires-Dist: mypy; extra == "dev"
Requires-Dist: pandas-stubs; extra == "dev"
Requires-Dist: pylint-pytest; extra == "dev"
Requires-Dist: pytest; extra == "dev"
Requires-Dist: pytest-cov; extra == "dev"
Requires-Dist: pytest-mock; extra == "dev"
Requires-Dist: radon; extra == "dev"
Requires-Dist: twine; extra == "dev"
Requires-Dist: types-pymysql; extra == "dev"
Requires-Dist: types-pyyaml; extra == "dev"
Dynamic: license-file
